chadplotlib/__init__.py
chadplotlib/fonts/Montserrat-Bold.ttf
chadplotlib/fonts/Montserrat-Medium.ttf
chadplotlib/fonts/Montserrat-Regular.ttf
chadplotlib-0.0.4.dist-info/METADATA
chadplotlib-0.0.4.dist-info/WHEEL
chadplotlib-0.0.4.dist-info/licenses/LICENSE
chadplotlib-0.0.4.dist-info/RECORD
