Metadata-Version: 2.4
Name: chadplotlib
Version: 0.0.4
Summary: Styling options for matplotlib.
Project-URL: Homepage, https://github.com/tdaron/chadplotlib
Project-URL: Issues, https://github.com/tdaron/chadplotlib/issues
Author-email: Théo Daron <theo@daron.be>, Maxime Deboeck <no-mail@plz.be>
License-File: LICENSE
Classifier: License :: OSI Approved :: MIT License
Classifier: Operating System :: OS Independent
Classifier: Programming Language :: Python :: 3
Requires-Python: >=3.7
